py_dotenv_safe/__init__.py
py_dotenv_safe/config.py
py_dotenv_safe/dotenv_safe.py
py_dotenv_safe/missing_env_vars_error.py
py_dotenv_safe-1.0.1.dist-info/LICENSE
py_dotenv_safe-1.0.1.dist-info/METADATA
py_dotenv_safe-1.0.1.dist-info/WHEEL
py_dotenv_safe-1.0.1.dist-info/entry_points.txt
py_dotenv_safe-1.0.1.dist-info/top_level.txt
py_dotenv_safe-1.0.1.dist-info/RECORD
