Metadata-Version: 2.1
Name: py_dotenv_safe
Version: 1.0.1
Summary: A robust Python library for managing environment variables with .env files, ensuring they are all present and correctly configured.
Home-page: https://github.com/jainiljakasaniya/py_dotenv_safe
Author: Jainil Jakasaniya
Author-email: jainiljakasaniya@gmail.com
License: MIT
Classifier: Programming Language :: Python :: 3
Classifier: License :: OSI Approved :: MIT License
Classifier: Operating System :: OS Independent
Requires-Python: >=3.6
License-File: LICENSE
Requires-Dist: python-dotenv >=1.0.1
